gridt/__init__.py
gridt/basetest.py
gridt/db.py
gridt/controllers/__init__.py
gridt/controllers/follower.py
gridt/controllers/helpers.py
gridt/controllers/leader.py
gridt/controllers/movements.py
gridt/controllers/test_follower.py
gridt/controllers/test_helpers.py
gridt/controllers/test_leader.py
gridt/controllers/test_movements.py
gridt/controllers/test_user.py
gridt/controllers/user.py
gridt/models/__init__.py
gridt/models/movement.py
gridt/models/movement_user_association.py
gridt/models/signal.py
gridt/models/test_movement.py
gridt/models/test_user.py
gridt/models/user.py
gridt/util/__init__.py
gridt/util/email_templates.py
gridt/util/nostderr.py
gridt/util/send_email.py
gridtlib-0.0.1.dist-info/METADATA
gridtlib-0.0.1.dist-info/WHEEL
gridtlib-0.0.1.dist-info/top_level.txt
gridtlib-0.0.1.dist-info/RECORD
