Metadata-Version: 2.1
Name: gridtlib
Version: 0.0.1
Summary: Library for interacting with the Gridt Network database.
Home-page: https://github.com/GridtNetwork/gridtlib
Author: Robin A. Dorstijn
Author-email: info@gridt.org
License: MIT license
Keywords: gridtlib
Platform: UNKNOWN
Classifier: Development Status :: 2 - Pre-Alpha
Classifier: Intended Audience :: Developers
Classifier: License :: OSI Approved :: MIT License
Classifier: Natural Language :: English
Classifier: Programming Language :: Python :: 3
Classifier: Programming Language :: Python :: 3.5
Classifier: Programming Language :: Python :: 3.6
Classifier: Programming Language :: Python :: 3.7
Classifier: Programming Language :: Python :: 3.8
Requires-Python: >=3.5
Requires-Dist: passlib
Requires-Dist: pyjwt
Requires-Dist: python-http-client
Requires-Dist: sendgrid
Requires-Dist: sqlalchemy
Requires-Dist: starkbank-ecdsa
